README.rst
setup.py
django_compressor_mako/__init__.py
django_compressor_mako.egg-info/PKG-INFO
django_compressor_mako.egg-info/SOURCES.txt
django_compressor_mako.egg-info/dependency_links.txt
django_compressor_mako.egg-info/not-zip-safe
django_compressor_mako.egg-info/top_level.txt
django_compressor_mako/management/__init__.py
django_compressor_mako/management/commands/compress_mako.py